Projekt JOS/zamek/counter.v
module counter#(parameter width = 4, parameter modulus = 10)(
    input clr,
    input clk,
    input ce,
    output reg [width - 1:0] data,
    output cout
);

    always @(posedge clk)
        if (clr)
            begin
                data <= {width{1'b0}};
            end
        else
            begin
                if(ce)
                    begin
                        if(data != (modulus - 1))
                            begin
                                data = data + 1;
                            end
                        else
                            begin
                                data = {width{1'b0}};
                            end
                    end
            end

    assign cout = ce & (data == (modulus - 1));
endmodule

counter_tb.v
`include "counter.v"

`timescale 1ns/100ps

module counter_tb();

reg clr;
reg clk;
reg ce;


wire [3:0] data_o;
wire [3:0] data_1;
wire cout;

counter UUT(clr, clk, ce, data_o, count);

counter UUT1(clr, clk, count, data_1, x);

initial 
    begin
    #0 clr = 1'b1; clk = 1'b0; ce = 1'b0;
    #10 ce = 1'b1;
    #10 clr = 1'b0;
    #4 ce = 1'b0;
    #18 ce = 1'b1;
    #300 $finish;
    end

initial
    begin
        forever begin
            #5 clk = ~clk;
        end
    end

initial
    begin
        $dumpfile("counter.vcd");
        $dumpvars;
        $dumpon;
    end


endmodule

Projekt JOS/zamek/counter.vcd
$date
	Fri Apr 26 23:17:35 2024
$end
$version
	Icarus Verilog
$end
$timescale
	100ps
$end
$scope module counter_tb $end
$var wire 1 ! x $end
$var wire 4 " data_o [3:0] $end
$var wire 4 # data_1 [3:0] $end
$var wire 1 $ count $end
$var reg 1 % ce $end
$var reg 1 & clk $end
$var reg 1 ' clr $end
$scope module UUT $end
$var wire 1 % ce $end
$var wire 1 & clk $end
$var wire 1 ' clr $end
$var wire 1 $ cout $end
$var parameter 32 ( modulus $end
$var parameter 32 ) width $end
$var reg 4 * data [3:0] $end
$upscope $end
$scope module UUT1 $end
$var wire 1 $ ce $end
$var wire 1 & clk $end
$var wire 1 ' clr $end
$var wire 1 ! cout $end
$var parameter 32 + modulus $end
$var parameter 32 , width $end
$var reg 4 - data [3:0] $end
$upscope $end
$upscope $end
$enddefinitions $end
$comment Show the parameter values. $end
$dumpall
b100 ,
b1010 +
b100 )
b1010 (
$end
#0
$dumpvars
bx -
bx *
1'
0&
0%
0$
bx #
bx "
0!
$end
#50
b0 "
b0 *
b0 #
b0 -
1&
#100
0&
1%
#150
1&
#200
0&
0'
#240
0%
#250
1&
#300
0&
#350
1&
#400
0&
#420
1%
#450
b1 "
b1 *
1&
#500
0&
#550
b10 "
b10 *
1&
#600
0&
#650
b11 "
b11 *
1&
#700
0&
#750
b100 "
b100 *
1&
#800
0&
#850
b101 "
b101 *
1&
#900
0&
#950
b110 "
b110 *
1&
#1000
0&
#1050
b111 "
b111 *
1&
#1100
0&
#1150
b1000 "
b1000 *
1&
#1200
0&
#1250
1$
b1001 "
b1001 *
1&
#1300
0&
#1350
0$
b1 #
b1 -
b0 "
b0 *
1&
#1400
0&
#1450
b1 "
b1 *
1&
#1500
0&
#1550
b10 "
b10 *
1&
#1600
0&
#1650
b11 "
b11 *
1&
#1700
0&
#1750
b100 "
b100 *
1&
#1800
0&
#1850
b101 "
b101 *
1&
#1900
0&
#1950
b110 "
b110 *
1&
#2000
0&
#2050
b111 "
b111 *
1&
#2100
0&
#2150
b1000 "
b1000 *
1&
#2200
0&
#2250
1$
b1001 "
b1001 *
1&
#2300
0&
#2350
0$
b10 #
b10 -
b0 "
b0 *
1&
#2400
0&
#2450
b1 "
b1 *
1&
#2500
0&
#2550
b10 "
b10 *
1&
#2600
0&
#2650
b11 "
b11 *
1&
#2700
0&
#2750
b100 "
b100 *
1&
#2800
0&
#2850
b101 "
b101 *
1&
#2900
0&
#2950
b110 "
b110 *
1&
#3000
0&
#3050
b111 "
b111 *
1&
#3100
0&
#3150
b1000 "
b1000 *
1&
#3200
0&
#3250
1$
b1001 "
b1001 *
1&
#3300
0&
#3350
0$
b11 #
b11 -
b0 "
b0 *
1&
