Projekt JOS/zamek/pipo.v
module pipo#(parameter width = 4)
    (
    input clr,
    input clk,
    input ce,
    input [width - 1:0] data_i,
    output reg [width - 1:0] data_o
);

always @(posedge clk or posedge clr) 
begin
    if (clr)
        begin
            data_o <= {width{1'b0}};
        end
    else if (clk)
        begin
            if (ce)
                        begin
                        data_o <= data_i;
                        end
        end

end

endmodule

Projekt JOS/zamek/shifting_pipo.v
`include "pipo.v"

module shifting_pipo
(
    input clr,
    input clk,
    input ce,
    input [3:0] data_in,
    output [15:0] data_o
);

pipo reg0(.clr(clr), .clk(clk), .ce(ce), .data_i(data_o[7:4]), .data_o(data_o[3:0]));
pipo reg1(.clr(clr), .clk(clk), .ce(ce), .data_i(data_o[11:8]), .data_o(data_o[7:4]));
pipo reg2(.clr(clr), .clk(clk), .ce(ce), .data_i(data_o[15:12]), .data_o(data_o[11:8]));
pipo reg3(.clr(clr), .clk(clk), .ce(ce), .data_i(data_in), .data_o(data_o[15:12]));



endmodule

ProjektJOS - Zamek/shifting_pipo_tb.v
`include "shifting_pipo.v"

module shifting_pipo_tb();

reg clr;
reg clk;
reg ce;
reg [3:0] data_i;
wire [15:0] data_o;

shifting_pipo UUT(clr, clk, ce, data_i, data_o);

initial 
    begin
    #0 clr = 1'b1; clk = 1'b0; ce = 1'b0; data_i = 4'd0;
    #10 ce = 1'b1;
    #10 clr = 1'b0;
    #10 data_i = 4'd1;
    #10 data_i = 4'd2;
    #4 ce = 1'b0;
    #18 ce = 1'b1;
    #10 data_i = 4'd3;
    #10 data_i = 4'd4;
    #20 clr = 1'b1;
    #10 $finish;
    end

initial
    begin
        forever begin
            #5 clk = ~clk;
        end
    end

initial
    begin
        $dumpfile("shifting_pipo.vcd");
        $dumpvars;
        $dumpon;
    end


endmodule

ProjektJOS - Zamek/shifting_pipo.vcd
$date
	Thu Apr 25 21:54:09 2024
$end
$version
	Icarus Verilog
$end
$timescale
	1s
$end
$scope module shifting_pipo_tb $end
$var wire 16 ! data_o [15:0] $end
$var reg 1 " ce $end
$var reg 1 # clk $end
$var reg 1 $ clr $end
$var reg 4 % data_i [3:0] $end
$scope module UUT $end
$var wire 1 " ce $end
$var wire 1 # clk $end
$var wire 1 $ clr $end
$var wire 4 & data_in [3:0] $end
$var wire 16 ' data_o [15:0] $end
$scope module reg0 $end
$var wire 1 " ce $end
$var wire 1 # clk $end
$var wire 1 $ clr $end
$var wire 4 ( data_i [3:0] $end
$var parameter 32 ) width $end
$var reg 4 * data_o [3:0] $end
$upscope $end
$scope module reg1 $end
$var wire 1 " ce $end
$var wire 1 # clk $end
$var wire 1 $ clr $end
$var wire 4 + data_i [3:0] $end
$var parameter 32 , width $end
$var reg 4 - data_o [3:0] $end
$upscope $end
$scope module reg2 $end
$var wire 1 " ce $end
$var wire 1 # clk $end
$var wire 1 $ clr $end
$var wire 4 . data_i [3:0] $end
$var parameter 32 / width $end
$var reg 4 0 data_o [3:0] $end
$upscope $end
$scope module reg3 $end
$var wire 1 " ce $end
$var wire 1 # clk $end
$var wire 1 $ clr $end
$var wire 4 1 data_i [3:0] $end
$var parameter 32 2 width $end
$var reg 4 3 data_o [3:0] $end
$upscope $end
$upscope $end
$upscope $end
$enddefinitions $end
$comment Show the parameter values. $end
$dumpall
b100 2
b100 /
b100 ,
b100 )
$end
#0
$dumpvars
b0 3
b0 1
b0 0
b0 .
b0 -
b0 +
b0 *
b0 (
b0 '
b0 &
b0 %
1$
0#
0"
b0 !
$end
#5
1#
#10
0#
1"
#15
1#
#20
0#
0$
#25
1#
#30
0#
b1 %
b1 &
b1 1
#35
b1 .
b1000000000000 !
b1000000000000 '
b1 3
1#
#40
0#
b10 %
b10 &
b10 1
#44
0"
#45
1#
#50
0#
#55
1#
#60
0#
#62
1"
#65
b10 .
b1 +
b10 3
b10000100000000 !
b10000100000000 '
b1 0
1#
#70
0#
#72
b11 %
b11 &
b11 1
#75
b1 (
b10 +
b11 .
b1 -
b10 0
b11001000010000 !
b11001000010000 '
b11 3
1#
#80
0#
#82
b100 %
b100 &
b100 1
#85
b100 .
b11 +
b10 (
b100 3
b11 0
b10 -
b100001100100001 !
b100001100100001 '
b1 *
1#
#90
0#
#95
b11 (
b100 +
b10 *
b11 -
b100010000110010 !
b100010000110010 '
b100 0
1#
#100
0#
#102
b0 .
b0 +
b0 (
b0 3
b0 0
b0 -
b0 !
b0 '
b0 *
1$
